drift/__init__.py
drift/adaptors.py
drift/convert.py
drift/drift.py
drift/exceptions.py
sdss_drift-1.2.0.dist-info/LICENSE.md
sdss_drift-1.2.0.dist-info/METADATA
sdss_drift-1.2.0.dist-info/WHEEL
sdss_drift-1.2.0.dist-info/RECORD
