Metadata-Version: 2.1
Name: sdss-drift
Version: 1.2.0
Summary: Modbus PLC control library
Home-page: https://github.com/sdss/drift
License: BSD-3-Clause
Keywords: astronomy,software
Author: José Sánchez-Gallego
Author-email: gallegoj@uw.edu
Requires-Python: >=3.8,<4.0
Classifier: Intended Audience :: Science/Research
Classifier: License :: OSI Approved :: BSD License
Classifier: Natural Language :: English
Classifier: Operating System :: OS Independent
Classifier: Programming Language :: Python :: 3
Classifier: Programming Language :: Python :: 3.8
Classifier: Programming Language :: Python :: 3.9
Classifier: Programming Language :: Python :: 3.10
Classifier: Programming Language :: Python :: 3.11
Classifier: Programming Language :: Python :: 3.12
Classifier: Programming Language :: Python :: 3.7
Classifier: Topic :: Documentation :: Sphinx
Classifier: Topic :: Software Development :: Libraries :: Python Modules
Requires-Dist: pymodbus (>=3.0.0,<4.0.0)
Requires-Dist: sdsstools (>=1.0.0,<2.0.0)
Project-URL: Documentation, https://sdss-drift.readthedocs.org
Project-URL: Repository, https://github.com/sdss/drift
